crontools/__about__.py
crontools/__init__.py
crontools/crontab.py
crontools/py.typed
crontools-0.1.6.dist-info/LICENSE
crontools-0.1.6.dist-info/WHEEL
crontools-0.1.6.dist-info/METADATA
crontools-0.1.6.dist-info/RECORD
